Workbook

Sheet 使い方
A1: 電気工事 見積書・請求書（インボイス対応） v1.0
A3: ■ 使い方（3ステップ）
A4: 1. 「自社情報」に屋号・登録番号・振込先を1回だけ入れる
A5: 2. 「見積書」に宛先・件名・明細を入れて印刷（またはPDF保存）
A6: 3. 工事が終わったら「請求書」の請求日・取引年月日を入れる。明細は見積書から自動で入ります。
A7: 見積後に決まった追加・変更工事だけ、請求書の「追加・変更工事」欄に入れてください（減額はマイナスの数量で）。
A9: ■ 色の意味
A10: ・黄色セル（青字）＝入力欄 ／ 水色セル＝自動（見積書・自社情報を参照しています。上書きしないでください）
A12: ■ インボイス（適格請求書）の記載事項との対応（国税庁「適格請求書等保存方式の概要」の記載事項）
A13: ・発行者の氏名または名称・登録番号 …… 自社情報 → 請求書の右上
A14: ・取引年月日 …… 請求書の「取引年月日」（工事の完了日）
A15: ・取引内容 …… 明細の品名・工事内容
... A24: 【免責】本ファイルは見積書・請求書の作成を補助するテンプレートです。インボイス制度・消費税の取扱いの最終判断は、国税庁の公表資料や税理士・税務署にご確認ください。

Sheet 自社情報
A1: 自社情報（ここに1回入れるだけで、見積書・請求書の両方に反映されます）
A2: 黄色セル（青字）＝入力欄
A4: 屋号・会社名 | B4: ○○電設
A5: 担当者 | B5: ○○
A6: 住所 | B6: ○○県○○市○○ 1-2-3
A7: 電話 | B7: 000-0000-0000
A8: 登録番号（インボイス） | B8: T0000000000000
A10: 振込先 銀行・支店 | B10: ○○銀行 ○○支店
A11: 振込先 種別・口座番号 | B11: 普通 0000000
A12: 振込先 口座名義 | B12: マルマル デンセツ
A14: 見積の有効期限（日数） | B14: 30
A15: 支払期限（請求日から日数） | B15: 30
A16: 消費税率 | B16: 0.1
A18: ※ 個人の方は、屋号がなければ氏名でもかまいません（実名を出したくない場合の扱いは税務署等にご確認ください）。

Sheet 見積書
A1: 御 見 積 書
A3: 宛先 | B3: ○○ 様 | C3: 見積日 | D3: =TODAY()
A4: 件名 | B4: ○○邸 電気設備工事 | C4: 有効期限 | D4: =IF(D3="","",D3+自社情報!$B$14)
A5: 工事場所 | B5: ○○市○○ | E5: 発行者 | F5: =IF(自社情報!$B$4="","",自社情報!$B$4)
A6: 見積番号 | B6: M-0001 | E6: 担当 | F6: =IF(自社情報!$B$5="","",自社情報!$B$5)
E7: 住所 | F7: =IF(自社情報!$B$6="","",自社情報!$B$6)
E8: 電話 | F8: =IF(自社情報!$B$7="","",自社情報!$B$7)
E9: 登録番号 | F9: =IF(自社情報!$B$8="","",自社情報!$B$8)
A11: 御見積金額（税込） | B11: =G36
A13: No | B13: 品名・工事内容 | C13: 規格・内容 | D13: 数量 | E13: 単位 | F13: 単価 | G13: 金額
A14: 1 | B14: 分電盤交換 | C14: 主幹50A 16回路 | D14: 1 | E14: 台 | F14: 48000 | G14: =IF(OR(D14="",F14=""),"",ROUND(D14*F14,0))
A15: 2 | B15: エアコン専用回路増設 | C15: VVF2.0-3C 15m程度 | D15: 2 | E15: 回路 | F15: 18000 | G15: =IF(OR(D15="",F15=""),"",ROUND(D15*F15,0))
A16: 3 | B16: コンセント増設 | C16: 2口 接地付 | D16: 3 | E16: 箇所 | F16: 6500 | G16: =IF(OR(D16="",F16=""),"",ROUND(D16*F16,0))
A17: 4 | B17: 材料・消耗品 | D17: 1 | E17: 式 | F17: 9800 | G17: =IF(OR(D17="",F17=""),"",ROUND(D17*F17,0))
A18: 5 | B18: 諸経費 | D18: 1 | E18: 式 | F18: 8000 | G18: =IF(OR(D18="",F18=""),"",ROUND(D18*F18,0))
A19: 6 | G19: =IF(OR(D19="",F19=""),"",ROUND(D19*F19,0))
A20: 7 | G20: =IF(OR(D20="",F20=""),"",ROUND(D20*F20,0))
A21: 8 | G21: =IF(OR(D21="",F21=""),"",ROUND(D21*F21,0))
A22: 9 | G22: =IF(OR(D22="",F22=""),"",ROUND(D22*F22,0))
A23: 10 | G23: =IF(OR(D23="",F23=""),"",ROUND(D23*F23,0))
A24: 11 | G24: =IF(OR(D24="",F24=""),"",ROUND(D24*F24,0))
A25: 12 | G25: =IF(OR(D25="",F25=""),"",ROUND(D25*F25,0))
A26: 13 | G26: =IF(OR(D26="",F26=""),"",ROUND(D26*F26,0))
A27: 14 | G27: =IF(OR(D27="",F27=""),"",ROUND(D27*F27,0))
A28: 15 | G28: =IF(OR(D28="",F28=""),"",ROUND(D28*F28,0))
A29: 16 | G29: =IF(OR(D29="",F29=""),"",ROUND(D29*F29,0))
A30: 17 | G30: =IF(OR(D30="",F30=""),"",ROUND(D30*F30,0))
... A33: 20 | G33: =IF(OR(D33="",F33=""),"",ROUND(D33*F33,0))
E34: 10%対象 小計 | G34: =SUM(G14:G33)
E35: 消費税（10%） | G35: =IF(N(自社情報!$B$16)<=0,"税率未入力",ROUNDDOWN(G34*自社情報!$B$16,0))
E36: 合計（税込） | G36: =IF(ISNUMBER(G35),G34+G35,"税率未入力")
A38: 備考 | B38: ・既設配線の不良等により追加工事が必要な場合は、事前にご相談のうえ別途お見積りいたします。

Sheet 請求書
A1: 請 求 書
A3: 宛先 | B3: =見積書!B3 | C3: 請求日 | D3: =TODAY()
A4: 件名 | B4: =見積書!B4 | C4: 取引年月日
A5: 工事場所 | B5: =見積書!B5 | C5: お支払期限 | D5: =IF(D3="","",D3+自社情報!$B$15) | E5: 発行者 | F5: =IF(自社情報!$B$4="","",自社情報!$B$4)
A6: 請求番号 | B6: S-0001 | E6: 担当 | F6: =IF(自社情報!$B$5="","",自社情報!$B$5)
E7: 住所 | F7: =IF(自社情報!$B$6="","",自社情報!$B$6)
E8: 電話 | F8: =IF(自社情報!$B$7="","",自社情報!$B$7)
E9: 登録番号 | F9: =IF(自社情報!$B$8="","",自社情報!$B$8)
A11: ご請求金額（税込） | B11: =G42
A13: No | B13: 品名・工事内容 | C13: 規格・内容 | D13: 数量 | E13: 単位 | F13: 単価 | G13: 金額
A14: 1 | B14: =IF(見積書!B14="","",見積書!B14) | C14: =IF(見積書!C14="","",見積書!C14) | D14: =IF(見積書!D14="","",見積書!D14) | E14: =IF(見積書!E14="","",見積書!E14) | F14: =IF(見積書!F14="","",見積書!F14) | G14: =IF(OR(D14="",F14=""),"",ROUND(D14*F14,0))
A15: 2 | B15: =IF(見積書!B15="","",見積書!B15) | C15: =IF(見積書!C15="","",見積書!C15) | D15: =IF(見積書!D15="","",見積書!D15) | E15: =IF(見積書!E15="","",見積書!E15) | F15: =IF(見積書!F15="","",見積書!F15) | G15: =IF(OR(D15="",F15=""),"",ROUND(D15*F15,0))
A16: 3 | B16: =IF(見積書!B16="","",見積書!B16) | C16: =IF(見積書!C16="","",見積書!C16) | D16: =IF(見積書!D16="","",見積書!D16) | E16: =IF(見積書!E16="","",見積書!E16) | F16: =IF(見積書!F16="","",見積書!F16) | G16: =IF(OR(D16="",F16=""),"",ROUND(D16*F16,0))
A17: 4 | B17: =IF(見積書!B17="","",見積書!B17) | C17: =IF(見積書!C17="","",見積書!C17) | D17: =IF(見積書!D17="","",見積書!D17) | E17: =IF(見積書!E17="","",見積書!E17) | F17: =IF(見積書!F17="","",見積書!F17) | G17: =IF(OR(D17="",F17=""),"",ROUND(D17*F17,0))
A18: 5 | B18: =IF(見積書!B18="","",見積書!B18) | C18: =IF(見積書!C18="","",見積書!C18) | D18: =IF(見積書!D18="","",見積書!D18) | E18: =IF(見積書!E18="","",見積書!E18) | F18: =IF(見積書!F18="","",見積書!F18) | G18: =IF(OR(D18="",F18=""),"",ROUND(D18*F18,0))
A19: 6 | B19: =IF(見積書!B19="","",見積書!B19) | C19: =IF(見積書!C19="","",見積書!C19) | D19: =IF(見積書!D19="","",見積書!D19) | E19: =IF(見積書!E19="","",見積書!E19) | F19: =IF(見積書!F19="","",見積書!F19) | G19: =IF(OR(D19="",F19=""),"",ROUND(D19*F19,0))
A20: 7 | B20: =IF(見積書!B20="","",見積書!B20) | C20: =IF(見積書!C20="","",見積書!C20) | D20: =IF(見積書!D20="","",見積書!D20) | E20: =IF(見積書!E20="","",見積書!E20) | F20: =IF(見積書!F20="","",見積書!F20) | G20: =IF(OR(D20="",F20=""),"",ROUND(D20*F20,0))
A21: 8 | B21: =IF(見積書!B21="","",見積書!B21) | C21: =IF(見積書!C21="","",見積書!C21) | D21: =IF(見積書!D21="","",見積書!D21) | E21: =IF(見積書!E21="","",見積書!E21) | F21: =IF(見積書!F21="","",見積書!F21) | G21: =IF(OR(D21="",F21=""),"",ROUND(D21*F21,0))
A22: 9 | B22: =IF(見積書!B22="","",見積書!B22) | C22: =IF(見積書!C22="","",見積書!C22) | D22: =IF(見積書!D22="","",見積書!D22) | E22: =IF(見積書!E22="","",見積書!E22) | F22: =IF(見積書!F22="","",見積書!F22) | G22: =IF(OR(D22="",F22=""),"",ROUND(D22*F22,0))
A23: 10 | B23: =IF(見積書!B23="","",見積書!B23) | C23: =IF(見積書!C23="","",見積書!C23) | D23: =IF(見積書!D23="","",見積書!D23) | E23: =IF(見積書!E23="","",見積書!E23) | F23: =IF(見積書!F23="","",見積書!F23) | G23: =IF(OR(D23="",F23=""),"",ROUND(D23*F23,0))
A24: 11 | B24: =IF(見積書!B24="","",見積書!B24) | C24: =IF(見積書!C24="","",見積書!C24) | D24: =IF(見積書!D24="","",見積書!D24) | E24: =IF(見積書!E24="","",見積書!E24) | F24: =IF(見積書!F24="","",見積書!F24) | G24: =IF(OR(D24="",F24=""),"",ROUND(D24*F24,0))
A25: 12 | B25: =IF(見積書!B25="","",見積書!B25) | C25: =IF(見積書!C25="","",見積書!C25) | D25: =IF(見積書!D25="","",見積書!D25) | E25: =IF(見積書!E25="","",見積書!E25) | F25: =IF(見積書!F25="","",見積書!F25) | G25: =IF(OR(D25="",F25=""),"",ROUND(D25*F25,0))
... A33: 20 | B33: =IF(見積書!B33="","",見積書!B33) | C33: =IF(見積書!C33="","",見積書!C33) | D33: =IF(見積書!D33="","",見積書!D33) | E33: =IF(見積書!E33="","",見積書!E33) | F33: =IF(見積書!F33="","",見積書!F33) | G33: =IF(OR(D33="",F33=""),"",ROUND(D33*F33,0))
A34: 追加・変更工事（見積後に決まったもの。減額はマイナスの数量で）
A35: 21 | G35: =IF(OR(D35="",F35=""),"",ROUND(D35*F35,0))
A36: 22 | G36: =IF(OR(D36="",F36=""),"",ROUND(D36*F36,0))
A37: 23 | G37: =IF(OR(D37="",F37=""),"",ROUND(D37*F37,0))
A38: 24 | G38: =IF(OR(D38="",F38=""),"",ROUND(D38*F38,0))
A39: 25 | G39: =IF(OR(D39="",F39=""),"",ROUND(D39*F39,0))
E40: 10%対象 小計 | G40: =SUM(G14:G39)
E41: 消費税（10%） | G41: =IF(N(自社情報!$B$16)<=0,"税率未入力",ROUNDDOWN(G40*自社情報!$B$16,0))
E42: 合計（税込） | G42: =IF(ISNUMBER(G41),G40+G41,"税率未入力")
A44: お振込先 | B44: =自社情報!$B$10&" "&自社情報!$B$11
B45: ="口座名義："&自社情報!$B$12
A46: ※振込手数料はご負担くださいますようお願いいたします。
A47: ※金額はすべて税率10%の対象です（軽減税率の対象品目はありません）。
